JimsDeXuexiBiji/README.md
JimsDeXuexiBiji/__init__.py
JimsDeXuexiBiji/__main__.py
JimsDeXuexiBiji/file.epub
JimsDeXuexiBiji/index.html
JimsDeXuexiBiji/css/__init__.py
JimsDeXuexiBiji/css/annotations.css
JimsDeXuexiBiji/css/main.css
JimsDeXuexiBiji/css/normalize.css
JimsDeXuexiBiji/css/popup.css
JimsDeXuexiBiji/font/__init__.py
JimsDeXuexiBiji/font/fontello.eot
JimsDeXuexiBiji/font/fontello.svg
JimsDeXuexiBiji/font/fontello.ttf
JimsDeXuexiBiji/font/fontello.woff
JimsDeXuexiBiji/img/__init__.py
JimsDeXuexiBiji/img/annotator-glyph-sprite.png
JimsDeXuexiBiji/img/annotator-icon-sprite.png
JimsDeXuexiBiji/img/apple-touch-icon.png
JimsDeXuexiBiji/img/cancelfullscreen.png
JimsDeXuexiBiji/img/close.png
JimsDeXuexiBiji/img/fullscreen.png
JimsDeXuexiBiji/img/loader.gif
JimsDeXuexiBiji/img/menu-icon.png
JimsDeXuexiBiji/img/save.png
JimsDeXuexiBiji/img/saved.png
JimsDeXuexiBiji/img/settings-s.png
JimsDeXuexiBiji/img/settings.png
JimsDeXuexiBiji/img/star.png
JimsDeXuexiBiji/js/__init__.py
JimsDeXuexiBiji/js/epub.js
JimsDeXuexiBiji/js/epub.min.js
JimsDeXuexiBiji/js/epub.min.map
JimsDeXuexiBiji/js/hooks.min.js
JimsDeXuexiBiji/js/hooks.min.map
JimsDeXuexiBiji/js/reader.js
JimsDeXuexiBiji/js/reader.js.map
JimsDeXuexiBiji/js/reader.min.js
JimsDeXuexiBiji/js/reader.min.map
JimsDeXuexiBiji/js/hooks/__init__.py
JimsDeXuexiBiji/js/hooks/extensions/__init__.py
JimsDeXuexiBiji/js/hooks/extensions/highlight.js
JimsDeXuexiBiji/js/libs/__init__.py
JimsDeXuexiBiji/js/libs/jquery.min.js
JimsDeXuexiBiji/js/libs/localforage.min.js
JimsDeXuexiBiji/js/libs/screenfull.js
JimsDeXuexiBiji/js/libs/screenfull.min.js
JimsDeXuexiBiji/js/libs/zip.min.js
JimsDeXuexiBiji/js/plugins/__init__.py
JimsDeXuexiBiji/js/plugins/hypothesis.js
JimsDeXuexiBiji/js/plugins/search.js
jims_de_xuexi_biji-2024.3.2.0.dist-info/METADATA
jims_de_xuexi_biji-2024.3.2.0.dist-info/WHEEL
jims_de_xuexi_biji-2024.3.2.0.dist-info/entry_points.txt
jims_de_xuexi_biji-2024.3.2.0.dist-info/top_level.txt
jims_de_xuexi_biji-2024.3.2.0.dist-info/RECORD
